MANIFEST.in
README.rst
setup.cfg
setup.py
pyke/__init__.py
pyke/keparray.py
pyke/kepbls.py
pyke/kepclean.py
pyke/kepclip.py
pyke/kepconvert.py
pyke/kepcotrend.py
pyke/kepdetrend.py
pyke/kepdiffim.py
pyke/kepdraw.py
pyke/kepdynamic.py
pyke/kepextract.py
pyke/kepffi.py
pyke/kepfilter.py
pyke/kepfit.py
pyke/kepflatten.py
pyke/kepfold.py
pyke/kepfourier.py
pyke/kepfunc.py
pyke/kephead.py
pyke/kepimages.py
pyke/kepio.py
pyke/kepkey.py
pyke/kepmask.py
pyke/kepmsg.py
pyke/kepoutlier.py
pyke/keppca.py
pyke/kepperiodogram.py
pyke/keppixseries.py
pyke/kepplot.py
pyke/kepprf.py
pyke/kepprfphot.py
pyke/keprange.py
pyke/kepsff.py
pyke/kepsmooth.py
pyke/kepstat.py
pyke/kepstddev.py
pyke/kepstitch.py
pyke/keptimefix.py
pyke/keptrial.py
pyke/keptrim.py
pyke/kepwindow.py
pyke/lightcurve.py
pyke/prf.py
pyke/sandbox.py
pyke/targetpixelfile.py
pyke/utils.py
pyke/version.py
pyketools.egg-info/PKG-INFO
pyketools.egg-info/SOURCES.txt
pyketools.egg-info/dependency_links.txt
pyketools.egg-info/entry_points.txt
pyketools.egg-info/requires.txt
pyketools.egg-info/top_level.txt