Metadata-Version: 1.1
Name: pyketools
Version: 3.1.0
Summary: Tools to inspect and analyze the pixels and lightcurves obtained by NASA's Kepler, K2, and TESS space telescopes.
Home-page: UNKNOWN
Author: KeplerGO
Author-email: keplergo@mail.arc.nasa.gov
License: MIT
Platform: UNKNOWN
Classifier: Development Status :: 5 - Production/Stable
Classifier: License :: OSI Approved :: MIT License
Classifier: Operating System :: OS Independent
Classifier: Programming Language :: Python
Classifier: Intended Audience :: Science/Research
Classifier: Topic :: Scientific/Engineering :: Astronomy
